{
  "configurations": {
    "Launch": {
      "adapter": "vscode-cpptools",
      "configuration": {
        "request": "launch",
        "program": "${fileDirname}/progr",
        "args": ["-e", "/home/pedro/Documents/t2-ed/", "-f", "geoname.geo", "-o",  "/home/pedro/Documents/t2-ed/output",  "-q", "qryname.qry"],
        "cwd": "${cwd}",
        "environment": [ ],
        "externalConsole": true,
		    "stopOnEntry": true,
		    "stopAtEntry": true,
        "MIMode": "gdb"
      }
    }
  }
}
